spiga/__init__.py
spiga/data/__init__.py
spiga/data/readme.md
spiga/data/annotations/300wprivate/db_info.json
spiga/data/annotations/300wpublic/db_info.json
spiga/data/annotations/cofw68/db_info.json
spiga/data/annotations/merlrav/db_info.json
spiga/data/annotations/wflw/db_info.json
spiga/data/loaders/__init__.py
spiga/data/loaders/alignments.py
spiga/data/loaders/dataloader.py
spiga/data/loaders/dl_config.py
spiga/data/loaders/transforms.py
spiga/data/loaders/augmentors/__init__.py
spiga/data/loaders/augmentors/boundary.py
spiga/data/loaders/augmentors/heatmaps.py
spiga/data/loaders/augmentors/landmarks.py
spiga/data/loaders/augmentors/modern_posit.py
spiga/data/loaders/augmentors/utils.py
spiga/data/models3D/__init__.py
spiga/data/models3D/mean_face_3D_68.txt
spiga/data/models3D/mean_face_3D_98.txt
spiga/data/models3D/visualization.py
spiga/data/visualize/__init__.py
spiga/data/visualize/inspect_dataset.py
spiga/data/visualize/inspect_heatmaps.py
spiga/data/visualize/plotting.py
spiga/demo/__init__.py
spiga/demo/app.py
spiga/demo/analyze/__init__.py
spiga/demo/analyze/analyzer.py
spiga/demo/analyze/extract/__init__.py
spiga/demo/analyze/extract/processor.py
spiga/demo/analyze/extract/spiga_processor.py
spiga/demo/analyze/features/__init__.py
spiga/demo/analyze/features/basic.py
spiga/demo/analyze/features/face.py
spiga/demo/analyze/track/__init__.py
spiga/demo/analyze/track/get_tracker.py
spiga/demo/analyze/track/tracker.py
spiga/demo/analyze/track/retinasort/__init__.py
spiga/demo/analyze/track/retinasort/config.py
spiga/demo/analyze/track/retinasort/face_tracker.py
spiga/demo/analyze/track/retinasort/zoo.py
spiga/demo/utils/__init__.py
spiga/demo/utils/frames2video.py
spiga/demo/visualize/__init__.py
spiga/demo/visualize/plotter.py
spiga/demo/visualize/viewer.py
spiga/demo/visualize/layouts/__init__.py
spiga/demo/visualize/layouts/plot_basics.py
spiga/demo/visualize/layouts/plot_bbox.py
spiga/demo/visualize/layouts/plot_headpose.py
spiga-0.0.6.dist-info/LICENSE
spiga-0.0.6.dist-info/METADATA
spiga-0.0.6.dist-info/WHEEL
spiga-0.0.6.dist-info/top_level.txt
spiga-0.0.6.dist-info/RECORD
