Metadata-Version: 2.1
Name: spiga
Version: 0.0.6
Summary: SPIGA: Shape Preserving Facial Landmarks with Graph Attention Networks
Home-page: https://github.com/andresprados/SPIGA
Author: Andres Prados Torreblanca
Author-email: andresprator@gmail.com
License: BSD-3-Clause
Project-URL: Homepage, https://bmvc2022.mpi-inf.mpg.de/155/
Project-URL: SPIGA Paper, https://bmvc2022.mpi-inf.mpg.de/0155.pdf
Project-URL: Bug Tracker, https://github.com/andresprados/SPIGA/issues
Keywords: Computer Vision,Face Alignment,Head Pose Estimation,Pytorch,CNN,GNN,BMVC2022,WFLW,300W,Merlrav,COFW
Classifier: Development Status :: 4 - Beta
Classifier: Intended Audience :: Developers
Classifier: Intended Audience :: Science/Research
Classifier: Intended Audience :: Education
Classifier: Operating System :: OS Independent
Classifier: Environment :: GPU
Classifier: Environment :: Console
Classifier: Programming Language :: Python :: 3
Classifier: Programming Language :: Python :: 3.7
Classifier: Programming Language :: Python :: 3.8
Classifier: Programming Language :: Python :: 3.9
Classifier: Programming Language :: Python :: 3.10
Classifier: Topic :: Scientific/Engineering :: Artificial Intelligence
Classifier: Topic :: Scientific/Engineering :: Image Processing
Classifier: Topic :: Software Development :: Libraries
Classifier: Topic :: Software Development :: Libraries :: Python Modules
Requires-Python: >=3.6
License-File: LICENSE
Requires-Dist: matplotlib (>=3.2.1)
Requires-Dist: numpy (>=1.18.2)
Requires-Dist: opencv-python (>=4.2.0.32)
Requires-Dist: Pillow (>=7.0.0)
Requires-Dist: torch (>=1.4.0)
Requires-Dist: torchvision (>=0.5.0)
Requires-Dist: torchaudio
Requires-Dist: scipy
Requires-Dist: scikit-learn
Provides-Extra: demo
Requires-Dist: retinaface-py (>=0.0.2) ; extra == 'demo'
Requires-Dist: sort-tracker-py (>=1.0.2) ; extra == 'demo'
